EVNTDispatch/__init__.py
EVNTDispatch/c_logger.py
EVNTDispatch/event_dispatcher.py
EVNTDispatch/event_listener.py
EVNTDispatch/event_type.py
EVNTDispatch/executor.py
EVNTDispatch/pevent.py
EVNTDispatch/utils.py
tests/__init__.py
tests/test_async_events.py
tests/test_dispatcher.py
tests/test_sync_events.py
EVNTDispatch-0.0.2.dist-info/LICENSE
EVNTDispatch-0.0.2.dist-info/METADATA
EVNTDispatch-0.0.2.dist-info/WHEEL
EVNTDispatch-0.0.2.dist-info/top_level.txt
EVNTDispatch-0.0.2.dist-info/RECORD
