Metadata-Version: 2.1
Name: EVNTDispatch
Version: 0.0.2
Summary: EVNTDispatch is a Python event system for seamless event-driven programming, offering flexibility and efficiency in handling and dispatching events.
Author: Curtidor
Author-email: tannermatos18@gmai.com
Keywords: EVNTDispatch,event system,event dispatcher,event-driven programming,synchronous events,asynchronous events,publish-subscribe,developer tools,Python 3,cross-platform
Classifier: Development Status :: 3 - Alpha
Classifier: Intended Audience :: Developers
Classifier: Programming Language :: Python :: 3
Classifier: Operating System :: Unix
Classifier: Operating System :: Microsoft :: Windows
License-File: LICENSE
Requires-Dist: pytest
